MANIFEST.in
README.rst
setup.py
GalvoController/__init__.py
GalvoController/config.py
GalvoController/favicon.ico
GalvoController/galvoController.py
GalvoController/galvoController.ui
GalvoController/galvoDriver.py
GalvoController/galvoGraphics.py
GalvoController/global_vars.py
GalvoController/laserConfig.ui
GalvoController.egg-info/PKG-INFO
GalvoController.egg-info/SOURCES.txt
GalvoController.egg-info/dependency_links.txt
GalvoController.egg-info/entry_points.txt
GalvoController.egg-info/requires.txt
GalvoController.egg-info/top_level.txt
GalvoController/images/USB6001_ports.PNG
GalvoController/images/freehand.png
GalvoController/images/line.png
GalvoController/images/point.png