Metadata-Version: 1.1
Name: GalvoController
Version: 0.0.5
Summary: 2D Galvonmeter laser control system with NIDAQ USB 6001 device
Home-page: UNKNOWN
Author: Brett Settle
Author-email: brettjsettle@gmail.com
License: MIT
Platform: UNKNOWN
Classifier: Intended Audience :: Science/Research
Classifier: Operating System :: OS Independent
Classifier: Programming Language :: Python
Classifier: Programming Language :: Python :: 3
Classifier: Programming Language :: Python :: 3.3
Classifier: Programming Language :: Python :: 3.4
Classifier: Programming Language :: Python :: 3.5
Classifier: Programming Language :: Python :: 3.6
Classifier: Topic :: Scientific/Engineering :: Visualization
